boxjelly/__init__.py
boxjelly/assets/assets.qrc
boxjelly/assets/icons/boxjelly.svg
boxjelly/assets/icons/boxjelly_logo.svg
boxjelly/assets/icons/delete.png
boxjelly/assets/icons/merge.png
boxjelly/assets/icons/redo.png
boxjelly/assets/icons/rename.png
boxjelly/assets/icons/seek_beginning.png
boxjelly/assets/icons/seek_end.png
boxjelly/assets/icons/split.png
boxjelly/assets/icons/undo.png
boxjelly/assets/images/boxjelly_logo_1024.png
boxjelly/assets/images/boxjelly_logo_128.png
boxjelly/assets/images/boxjelly_logo_256.png
boxjelly/assets/images/boxjelly_logo_512.png
boxjelly/commands/TrackListCommand.py
boxjelly/commands/__init__.py
boxjelly/delegates/TrackHeadersDelegate.py
boxjelly/delegates/__init__.py
boxjelly/lib/__init__.py
boxjelly/lib/constants.py
boxjelly/lib/fileio.py
boxjelly/lib/resources.py
boxjelly/lib/settings.py
boxjelly/lib/track.py
boxjelly/lib/util.py
boxjelly/models/TrackListModel.py
boxjelly/models/__init__.py
boxjelly/scripts/__init__.py
boxjelly/scripts/run.py
boxjelly/ui/FileSelector.py
boxjelly/ui/MainWindow.py
boxjelly/ui/MediaSelectionBox.py
boxjelly/ui/OpenDialog.py
boxjelly/ui/SourceWidgets.py
boxjelly/ui/TrackSelectionBox.py
boxjelly/ui/WidgetComboBox.py
boxjelly/ui/__init__.py
boxjelly/ui/graphicsitems/TimelineTrack.py
boxjelly/ui/graphicsitems/__init__.py
boxjelly/ui/settings/SettingsDialog.py
boxjelly/ui/settings/__init__.py
boxjelly/ui/settings/tabs/AbstractSettingsTab.py
boxjelly/ui/settings/tabs/NetworkSettingsTab.py
boxjelly/ui/settings/tabs/VideoSettingsTab.py
boxjelly/ui/settings/tabs/__init__.py
boxjelly/ui/track/Timeline.py
boxjelly/ui/track/TrackGraphicsView.py
boxjelly/ui/track/TrackHeadersView.py
boxjelly/ui/track/TrackPanel.py
boxjelly/ui/track/__init__.py
boxjelly/ui/video/CthulhuVideoController.py
boxjelly/ui/video/__init__.py
boxjelly-0.3.3.dist-info/LICENSE
boxjelly-0.3.3.dist-info/METADATA
boxjelly-0.3.3.dist-info/WHEEL
boxjelly-0.3.3.dist-info/entry_points.txt
boxjelly-0.3.3.dist-info/RECORD
