Metadata-Version: 2.1
Name: boxjelly
Version: 0.3.3
Summary: BoxJelly is a tool for viewing and editing object tracks in video.
License: MIT
Author: Kevin Barnard
Author-email: kbarnard@mbari.org
Requires-Python: >=3.8,<4.0
Classifier: License :: OSI Approved :: MIT License
Classifier: Programming Language :: Python :: 3
Classifier: Programming Language :: Python :: 3.8
Classifier: Programming Language :: Python :: 3.9
Classifier: Programming Language :: Python :: 3.10
Classifier: Programming Language :: Python :: 3.11
Requires-Dist: PyQt6 (>=6.3.1,<7.0.0)
Requires-Dist: dataclasses-json (>=0.5.7,<0.6.0)
Requires-Dist: intervaltree (>=3.1.0,<4.0.0)
Requires-Dist: sharktopoda-client (>=0.1.4,<0.2.0)
